pittgoogle/__init__.py
pittgoogle/alert.py
pittgoogle/auth.py
pittgoogle/bigquery.py
pittgoogle/exceptions.py
pittgoogle/pubsub.py
pittgoogle/registry.py
pittgoogle/registry_manifests/schemas.yml
pittgoogle/schema.py
pittgoogle/schemas/elasticc/elasticc.v0_9_1.alert.avsc
pittgoogle/schemas/elasticc/elasticc.v0_9_1.brokerClassification.avsc
pittgoogle/schemas/elasticc/elasticc.v0_9_1.diaForcedSource.avsc
pittgoogle/schemas/elasticc/elasticc.v0_9_1.diaNondetectionLimit.avsc
pittgoogle/schemas/elasticc/elasticc.v0_9_1.diaObject.avsc
pittgoogle/schemas/elasticc/elasticc.v0_9_1.diaSource.avsc
pittgoogle/schemas/lsst/10/0/lsst.v10_0.alert.avsc
pittgoogle/schemas/lsst/10/0/lsst.v10_0.diaForcedSource.avsc
pittgoogle/schemas/lsst/10/0/lsst.v10_0.diaObject.avsc
pittgoogle/schemas/lsst/10/0/lsst.v10_0.diaSource.avsc
pittgoogle/schemas/lsst/10/0/lsst.v10_0.mpc_orbits.avsc
pittgoogle/schemas/lsst/10/0/lsst.v10_0.ssObject.avsc
pittgoogle/schemas/lsst/10/0/lsst.v10_0.ssSource.avsc
pittgoogle/schemas/lsst/7/0/lsst.v7_0.alert.avsc
pittgoogle/schemas/lsst/7/0/lsst.v7_0.diaForcedSource.avsc
pittgoogle/schemas/lsst/7/0/lsst.v7_0.diaNondetectionLimit.avsc
pittgoogle/schemas/lsst/7/0/lsst.v7_0.diaObject.avsc
pittgoogle/schemas/lsst/7/0/lsst.v7_0.diaSource.avsc
pittgoogle/schemas/lsst/7/0/lsst.v7_0.ssObject.avsc
pittgoogle/schemas/lsst/7/1/lsst.v7_1.alert.avsc
pittgoogle/schemas/lsst/7/1/lsst.v7_1.diaForcedSource.avsc
pittgoogle/schemas/lsst/7/1/lsst.v7_1.diaNondetectionLimit.avsc
pittgoogle/schemas/lsst/7/1/lsst.v7_1.diaObject.avsc
pittgoogle/schemas/lsst/7/1/lsst.v7_1.diaSource.avsc
pittgoogle/schemas/lsst/7/1/lsst.v7_1.ssObject.avsc
pittgoogle/schemas/lsst/7/2/lsst.v7_2.alert.avsc
pittgoogle/schemas/lsst/7/2/lsst.v7_2.diaForcedSource.avsc
pittgoogle/schemas/lsst/7/2/lsst.v7_2.diaNondetectionLimit.avsc
pittgoogle/schemas/lsst/7/2/lsst.v7_2.diaObject.avsc
pittgoogle/schemas/lsst/7/2/lsst.v7_2.diaSource.avsc
pittgoogle/schemas/lsst/7/2/lsst.v7_2.ssObject.avsc
pittgoogle_client-0.3.20.dist-info/METADATA
pittgoogle_client-0.3.20.dist-info/WHEEL
pittgoogle_client-0.3.20.dist-info/licenses/LICENSE.txt
pittgoogle_client-0.3.20.dist-info/RECORD
