Metadata-Version: 2.4
Name: pittgoogle-client
Version: 0.3.20
Summary: Client utilities for the Pitt-Google astronomical alert broker.
License: BSD-3-Clause
License-File: LICENSE.txt
Keywords: astronomy,alert,broker,rubin
Author: MWV Research Group
Requires-Python: >=3.9,<4.0
Classifier: Intended Audience :: Science/Research
Classifier: License :: OSI Approved :: BSD License
Classifier: Programming Language :: Python :: 3
Classifier: Programming Language :: Python :: 3.9
Classifier: Programming Language :: Python :: 3.10
Classifier: Programming Language :: Python :: 3.11
Classifier: Programming Language :: Python :: 3.12
Classifier: Programming Language :: Python :: 3.13
Classifier: Programming Language :: Python :: 3.14
Classifier: Programming Language :: Python :: 3 :: Only
Classifier: Topic :: Scientific/Engineering :: Astronomy
Classifier: Topic :: Scientific/Engineering :: Physics
Classifier: Typing :: Typed
Requires-Dist: astropy (>=5.3)
Requires-Dist: attrs (>=23.1)
Requires-Dist: db-dtypes (>=1.2.0,<2.0.0)
Requires-Dist: fastavro (>=1.7.4)
Requires-Dist: google-auth-oauthlib (>=1.0)
Requires-Dist: google-cloud-bigquery (>=3.11.2)
Requires-Dist: google-cloud-functions (>=1.16.3)
Requires-Dist: google-cloud-pubsub (>=2.17.1)
Requires-Dist: hpgeom (>=1.3)
Requires-Dist: pandas (>=1.5)
Requires-Dist: tabulate (>=0.9)
Project-URL: Repository, https://github.com/mwvgroup/pittgoogle-client
